{
  "source": "00-assets/spreadsheet/Youth Intake.xlsx",
  "sheetsUsed": {
    "database": "Current Intake",
    "intakeList": "Intake List",
    "positionFocus": ""
  },
  "tierMapping": {
    "Tier 1 Premier": "CLB",
    "Tier 2 Europa": "ELB",
    "Tier 3 Conference": "ECL"
  },
  "teams": [
    {
      "team": "AC Milan",
      "tierRaw": "",
      "tier": "",
      "positionFocus": "",
      "intakePlayers": [
        {
          "name": "Kirk Hinrich",
          "tierRaw": "",
          "tier": ""
        },
        {
          "name": "Naz Reid",
          "tierRaw": "",
          "tier": ""
        }
      ]
    },
    {
      "team": "AFC Richmond",
      "tierRaw": "",
      "tier": "",
      "positionFocus": "",
      "intakePlayers": [
        {
          "name": "Walker Kessler",
          "tierRaw": "",
          "tier": ""
        },
        {
          "name": "Alex Len",
          "tierRaw": "",
          "tier": ""
        }
      ]
    },
    {
      "team": "Ajax",
      "tierRaw": "",
      "tier": "",
      "positionFocus": "",
      "intakePlayers": [
        {
          "name": "Sebastian Telfair",
          "tierRaw": "",
          "tier": ""
        },
        {
          "name": "Wayne Ellington",
          "tierRaw": "",
          "tier": ""
        },
        {
          "name": "Scott Skiles",
          "tierRaw": "",
          "tier": ""
        }
      ]
    },
    {
      "team": "Arsenal",
      "tierRaw": "",
      "tier": "",
      "positionFocus": "",
      "intakePlayers": [
        {
          "name": "Ousmane Dieng",
          "tierRaw": "",
          "tier": ""
        },
        {
          "name": "Richard Anderson",
          "tierRaw": "",
          "tier": ""
        },
        {
          "name": "Coby White",
          "tierRaw": "",
          "tier": ""
        }
      ]
    },
    {
      "team": "Aston Villa",
      "tierRaw": "",
      "tier": "",
      "positionFocus": "",
      "intakePlayers": [
        {
          "name": "Xavier McDaniel",
          "tierRaw": "",
          "tier": ""
        },
        {
          "name": "Oliver Miller",
          "tierRaw": "",
          "tier": ""
        },
        {
          "name": "Michael Ansley",
          "tierRaw": "",
          "tier": ""
        },
        {
          "name": "Matt Barnes",
          "tierRaw": "",
          "tier": ""
        }
      ]
    },
    {
      "team": "Atletico Madrid",
      "tierRaw": "",
      "tier": "",
      "positionFocus": "",
      "intakePlayers": [
        {
          "name": "Josh Richardson",
          "tierRaw": "",
          "tier": ""
        },
        {
          "name": "Damian Jones",
          "tierRaw": "",
          "tier": ""
        }
      ]
    },
    {
      "team": "Barcelona",
      "tierRaw": "",
      "tier": "",
      "positionFocus": "",
      "intakePlayers": [
        {
          "name": "Festus Ezeli",
          "tierRaw": "",
          "tier": ""
        },
        {
          "name": "Dan McClintock",
          "tierRaw": "",
          "tier": ""
        },
        {
          "name": "Jalen Duren",
          "tierRaw": "",
          "tier": ""
        },
        {
          "name": "Myles Turner",
          "tierRaw": "",
          "tier": ""
        }
      ]
    },
    {
      "team": "Bayern Munich",
      "tierRaw": "",
      "tier": "",
      "positionFocus": "",
      "intakePlayers": [
        {
          "name": "Rex Walters",
          "tierRaw": "",
          "tier": ""
        },
        {
          "name": "Tre Mann",
          "tierRaw": "",
          "tier": ""
        }
      ]
    },
    {
      "team": "Benfica",
      "tierRaw": "",
      "tier": "",
      "positionFocus": "",
      "intakePlayers": [
        {
          "name": "Cameron Thomas",
          "tierRaw": "",
          "tier": ""
        },
        {
          "name": "Eric White",
          "tierRaw": "",
          "tier": ""
        },
        {
          "name": "Chris Bosh",
          "tierRaw": "",
          "tier": ""
        }
      ]
    },
    {
      "team": "Brighton",
      "tierRaw": "",
      "tier": "",
      "positionFocus": "",
      "intakePlayers": [
        {
          "name": "Greg Anthony",
          "tierRaw": "",
          "tier": ""
        },
        {
          "name": "Jeff Grayer",
          "tierRaw": "",
          "tier": ""
        }
      ]
    },
    {
      "team": "Chelsea",
      "tierRaw": "",
      "tier": "",
      "positionFocus": "",
      "intakePlayers": [
        {
          "name": "Ricky Davis",
          "tierRaw": "",
          "tier": ""
        },
        {
          "name": "Kenny Battle",
          "tierRaw": "",
          "tier": ""
        },
        {
          "name": "Chet Holmgren",
          "tierRaw": "",
          "tier": ""
        }
      ]
    },
    {
      "team": "Crystal Palace",
      "tierRaw": "",
      "tier": "",
      "positionFocus": "",
      "intakePlayers": [
        {
          "name": "Steve Kerr",
          "tierRaw": "",
          "tier": ""
        },
        {
          "name": "Fred Roberts",
          "tierRaw": "",
          "tier": ""
        }
      ]
    },
    {
      "team": "Inter Milan",
      "tierRaw": "",
      "tier": "",
      "positionFocus": "",
      "intakePlayers": [
        {
          "name": "David West",
          "tierRaw": "",
          "tier": ""
        },
        {
          "name": "Cody Martin",
          "tierRaw": "",
          "tier": ""
        },
        {
          "name": "Derrick Favors",
          "tierRaw": "",
          "tier": ""
        },
        {
          "name": "Ozell Jones",
          "tierRaw": "",
          "tier": ""
        }
      ]
    },
    {
      "team": "Juventus",
      "tierRaw": "",
      "tier": "",
      "positionFocus": "",
      "intakePlayers": [
        {
          "name": "Ron Anderson",
          "tierRaw": "",
          "tier": ""
        },
        {
          "name": "Kyle O'Quinn",
          "tierRaw": "",
          "tier": ""
        },
        {
          "name": "Semih Erden",
          "tierRaw": "",
          "tier": ""
        }
      ]
    },
    {
      "team": "Liverpool",
      "tierRaw": "",
      "tier": "",
      "positionFocus": "",
      "intakePlayers": [
        {
          "name": "J.J. Redick",
          "tierRaw": "",
          "tier": ""
        },
        {
          "name": "Fred Roberts",
          "tierRaw": "",
          "tier": ""
        },
        {
          "name": "Davis Bertans",
          "tierRaw": "",
          "tier": ""
        },
        {
          "name": "Vincent Askew",
          "tierRaw": "",
          "tier": ""
        }
      ]
    },
    {
      "team": "Manchester City",
      "tierRaw": "",
      "tier": "",
      "positionFocus": "",
      "intakePlayers": [
        {
          "name": "Theo Ratliff",
          "tierRaw": "",
          "tier": ""
        },
        {
          "name": "Naji Marshall",
          "tierRaw": "",
          "tier": ""
        },
        {
          "name": "Eddy Curry",
          "tierRaw": "",
          "tier": ""
        },
        {
          "name": "John Stroeder",
          "tierRaw": "",
          "tier": ""
        }
      ]
    },
    {
      "team": "Manchester United",
      "tierRaw": "",
      "tier": "",
      "positionFocus": "",
      "intakePlayers": [
        {
          "name": "George McCloud",
          "tierRaw": "",
          "tier": ""
        },
        {
          "name": "Dirk Minniefield",
          "tierRaw": "",
          "tier": ""
        }
      ]
    },
    {
      "team": "Marseille",
      "tierRaw": "",
      "tier": "",
      "positionFocus": "",
      "intakePlayers": [
        {
          "name": "Bonzi Wells",
          "tierRaw": "",
          "tier": ""
        },
        {
          "name": "John Battle",
          "tierRaw": "",
          "tier": ""
        },
        {
          "name": "Harold Keeling",
          "tierRaw": "",
          "tier": ""
        }
      ]
    },
    {
      "team": "Monaco",
      "tierRaw": "",
      "tier": "",
      "positionFocus": "",
      "intakePlayers": [
        {
          "name": "Furkan Korkmaz",
          "tierRaw": "",
          "tier": ""
        },
        {
          "name": "Timofey Mozgov",
          "tierRaw": "",
          "tier": ""
        },
        {
          "name": "Andre Drummond",
          "tierRaw": "",
          "tier": ""
        }
      ]
    },
    {
      "team": "Paris Saint-Germain",
      "tierRaw": "",
      "tier": "",
      "positionFocus": "",
      "intakePlayers": [
        {
          "name": "Jrue Holiday",
          "tierRaw": "",
          "tier": ""
        },
        {
          "name": "Jaylin Williams",
          "tierRaw": "",
          "tier": ""
        },
        {
          "name": "Greg Grant",
          "tierRaw": "",
          "tier": ""
        },
        {
          "name": "Steve Nash",
          "tierRaw": "",
          "tier": ""
        }
      ]
    },
    {
      "team": "Real Madrid",
      "tierRaw": "",
      "tier": "",
      "positionFocus": "",
      "intakePlayers": [
        {
          "name": "John Paxson",
          "tierRaw": "",
          "tier": ""
        },
        {
          "name": "Kobe Brown",
          "tierRaw": "",
          "tier": ""
        }
      ]
    },
    {
      "team": "Sporting CP",
      "tierRaw": "",
      "tier": "",
      "positionFocus": "",
      "intakePlayers": [
        {
          "name": "Trayce Jackson-Davis",
          "tierRaw": "",
          "tier": ""
        },
        {
          "name": "Killian Hayes",
          "tierRaw": "",
          "tier": ""
        },
        {
          "name": "Larry Robinson",
          "tierRaw": "",
          "tier": ""
        },
        {
          "name": "Jalen Jones",
          "tierRaw": "",
          "tier": ""
        }
      ]
    },
    {
      "team": "Tottenham Hotspur",
      "tierRaw": "",
      "tier": "",
      "positionFocus": "",
      "intakePlayers": [
        {
          "name": "Kurt Thomas",
          "tierRaw": "",
          "tier": ""
        },
        {
          "name": "DeMarre Carroll",
          "tierRaw": "",
          "tier": ""
        },
        {
          "name": "Vincent Askew",
          "tierRaw": "",
          "tier": ""
        },
        {
          "name": "Doug Christie",
          "tierRaw": "",
          "tier": ""
        }
      ]
    },
    {
      "team": "Valencia",
      "tierRaw": "",
      "tier": "",
      "positionFocus": "",
      "intakePlayers": [
        {
          "name": "Jamaal Tinsley",
          "tierRaw": "",
          "tier": ""
        },
        {
          "name": "Maxi Kleber",
          "tierRaw": "",
          "tier": ""
        },
        {
          "name": "A.C. Green",
          "tierRaw": "",
          "tier": ""
        },
        {
          "name": "Chris Johnson",
          "tierRaw": "",
          "tier": ""
        }
      ]
    }
  ],
  "counts": {
    "teams": 24,
    "databasePlayers": 72
  }
}
